{
    "main": {
        "name": "Cindy Pham",
        "description": "Full Stack Web Developer | Game Developer | Android Application Developer",
        "image": "profilepic.jpg",
        "bio": "I am currently an AI Quality Controller at TELUS International. I have a Bachelor's in Computer Science and an Associate's in Mathematics. My hobbies include playing the piano, guitar, and violin, producing music, building Legos, and developing games. I am currently seeking a full-time role as a software engineer.",
        "contactmessage": "Contact Me",
        "email": "phamcindy619@utexas.edu",
        "phone": "(512) 903-8260",
        "address": {
            "city": "Austin",
            "state": "Texas"
        },
        "resumedownload": "CindyPham_Resume.pdf",
        "social": [
            {
                "name": "facebook",
                "url": "https://www.facebook.com/cindypham619",
                "className": "fa fa-facebook"
            },
            {
                "name": "linkedin",
                "url": "https://www.linkedin.com/in/phamcindy619",
                "className": "fa fa-linkedin"
            },
            {
                "name": "instagram",
                "url": "https://www.instagram.com/phamc619",
                "className": "fa fa-instagram"
            },
            {
                "name": "github",
                "url": "https://github.com/phamcindy619",
                "className": "fa fa-github"
            }
        ]
    },
    "resume": {
        "education": [
            {
                "school": "University of Texas at Austin",
                "degree": "Bachelor's in Computer Science",
                "graduated": "May 2021",
                "courses": "Matrix Calculations, Probability & Statistics, Data Structures, Discrete Mathematics, Computer Architecture, Information Retrieval, Operating Systems, Algorithms, Computer Networks, Network Security & Privacy, Modern Web Applications, Game Technology, Data Management, Software Engineering, Competitive Programming, Object-Oriented Programming, Ethical Foundations of CS",
                "clubs": "K-Beat Dance Team, Electronic Game Developers Society, Information & Systems Security Society, Texas Music Producers, Longhorn Gaming, Society of Asian Scientists and Engineers, IEEE Computer Society"
            },
            {
                "school": "Austin Community College",
                "degree": "Associate's in Mathematics",
                "graduated": "May 2017"
            }
        ],
        "work": [
            {
                "company": "TELUS International",
                "title": "AI Quality Controller",
                "years": "May 2022",
                "description": "Evaluate quality of AI-generated responses to user queries based on pre-defined guidelines; Analyze and provide feedback to improve user experience; Review and rate relevance of result blocks returned from search engine queries"
            },
            {
                "company": "SparkCognition",
                "title": "Winter Break Intern",
                "years": "January 2021",
                "description": "Work with team of 4 to provide quality assurance for DeepNLP software product; Automate information retrieval and document classification on large, unstructured datasets; Present metrics based on AI's performance accuracy and provided feedback on user experience"
            }
        ],
        "skills": {
            "languages": [
                "Java",
                "Python",
                "C/C++",
                "C#",
                "HTML",
                "CSS",
                "Javascript",
                "Typescript",
                "SQL",
                "x86 Assembly",
                "R"
            ],
            "frameworks": [
                "Git",
                "Unity",
                "React.js",
                "Flask",
                "Docker",
                "Godot",
                "Bootstrap",
                "Android Studio",
                "Google Cloud",
                "MySQL",
                "Linux",
                "Selenium",
                "Postman"
            ]
        }
    }
}